dynamic_leftpad/Leftpad.py
dynamic_leftpad/__init__.py
dynamic_leftpad-1.0.1.dist-info/licenses/LICENSE
dynamic_leftpad-1.0.1.dist-info/METADATA
dynamic_leftpad-1.0.1.dist-info/WHEEL
dynamic_leftpad-1.0.1.dist-info/top_level.txt
dynamic_leftpad-1.0.1.dist-info/RECORD
