Metadata-Version: 2.4
Name: dynamic-leftpad
Version: 1.0.1
Summary: Leftpad but python
Author-email: howShouldIChosseMyUsername <trademark2179@gmail.com>
License: MIT
Requires-Python: >=3.7
License-File: LICENSE
Dynamic: license-file
